netbox_kea/__init__.py
netbox_kea/constants.py
netbox_kea/filtersets.py
netbox_kea/forms.py
netbox_kea/graphql.py
netbox_kea/kea.py
netbox_kea/models.py
netbox_kea/navigation.py
netbox_kea/tables.py
netbox_kea/urls.py
netbox_kea/utilities.py
netbox_kea/views.py
netbox_kea/api/__init__.py
netbox_kea/api/serializers.py
netbox_kea/api/urls.py
netbox_kea/api/views.py
netbox_kea/migrations/0001_initial.py
netbox_kea/migrations/0002_alter_server_options_server_dhcp4_server_dhcp6.py
netbox_kea/migrations/__init__.py
netbox_kea/templates/netbox_kea/exception_htmx.html
netbox_kea/templates/netbox_kea/server.html
netbox_kea/templates/netbox_kea/server_dhcp_leases.html
netbox_kea/templates/netbox_kea/server_dhcp_leases_htmx.html
netbox_kea/templates/netbox_kea/server_dhcp_subnets.html
netbox_kea/templates/netbox_kea/server_status.html
netbox_kea/templates/netbox_kea/inc/server_dhcp_leases_paginator.html
netbox_kea-1.0.3.dist-info/METADATA
netbox_kea-1.0.3.dist-info/WHEEL
netbox_kea-1.0.3.dist-info/licenses/LICENSE
netbox_kea-1.0.3.dist-info/RECORD
