Metadata-Version: 2.4
Name: netbox-kea
Version: 1.0.3
Author-email: Devon Mar <devon-mar@users.noreply.github.com>
License-File: LICENSE
Requires-Python: >=3.10
Requires-Dist: netaddr<2.0.0,>=0.8
Requires-Dist: requests<3.0.0,>=2.0.0
